pyspark_flame/__init__.py
pyspark_flame-0.2.7.data/scripts/flamegraph.pl
pyspark_flame-0.2.7.dist-info/LICENSE
pyspark_flame-0.2.7.dist-info/METADATA
pyspark_flame-0.2.7.dist-info/WHEEL
pyspark_flame-0.2.7.dist-info/top_level.txt
pyspark_flame-0.2.7.dist-info/RECORD
