Metadata-Version: 2.1
Name: pyspark-flame
Version: 0.2.7
Summary: A low-overhead sampling profiler for PySpark, that outputs Flame Graphs
Home-page: https://github.com/jamespic/pyspark-flame
Author: James Pickering
Author-email: james_pic@hotmail.com
License: MIT
Platform: UNKNOWN
Classifier: Programming Language :: Python :: 2
Classifier: Programming Language :: Python :: 2.7
Classifier: Programming Language :: Python :: 3
Classifier: Programming Language :: Python :: 3.4
Classifier: Programming Language :: Python :: 3.5
Classifier: Programming Language :: Python :: 3.6
Classifier: Programming Language :: Python :: 3.7
Classifier: Programming Language :: Python :: 3.8
Requires-Dist: pyspark
